canonical_phone/__init__.py
canonical_phone/phone.py
canonical_phone-0.0.6.dist-info/LICENSE
canonical_phone-0.0.6.dist-info/METADATA
canonical_phone-0.0.6.dist-info/WHEEL
canonical_phone-0.0.6.dist-info/top_level.txt
canonical_phone-0.0.6.dist-info/RECORD
