Metadata-Version: 2.1
Name: canonical-phone
Version: 0.0.6
Summary: Library to get canonical phone number
Home-page: https://gitlab.com/nitinsureshp/canonical-phone.git
Author: Nitin Suresh
Author-email: nitin.kalal@pasarpolis.com
License: MIT
Platform: UNKNOWN
Classifier: Programming Language :: Python :: 3
Classifier: License :: OSI Approved :: MIT License
Classifier: Operating System :: OS Independent
Requires-Python: >=3.6
